flask_iniconfig.py
Flask_INIConfig-0.1.0.dist-info/DESCRIPTION.rst
Flask_INIConfig-0.1.0.dist-info/METADATA
Flask_INIConfig-0.1.0.dist-info/RECORD
Flask_INIConfig-0.1.0.dist-info/WHEEL
Flask_INIConfig-0.1.0.dist-info/metadata.json
Flask_INIConfig-0.1.0.dist-info/top_level.txt
