Metadata-Version: 2.0
Name: Flask-INIConfig
Version: 0.1.0
Summary: A flask extension to load ini files via config
Home-page: https://bitbucket.org/wampeter/flask-iniconfig/
Author: Wampeter Foma
Author-email: foma@wampeter.org
License: BSD
Platform: any
Classifier: Environment :: Web Environment
Classifier: Intended Audience :: Developers
Classifier: License :: OSI Approved :: BSD License
Classifier: Operating System :: OS Independent
Classifier: Programming Language :: Python
Classifier: Topic :: Internet :: WWW/HTTP :: Dynamic Content
Classifier: Topic :: Software Development :: Libraries :: Python Modules
Requires-Dist: Flask
